setup.py
teamlab/__init__.py
teamlab.egg-info/PKG-INFO
teamlab.egg-info/SOURCES.txt
teamlab.egg-info/dependency_links.txt
teamlab.egg-info/top_level.txt