Metadata-Version: 1.1
Name: teamlab
Version: 0.2
Summary: Python interface to TeamLab API
Home-page: http://code.umonkey.net/python-teamlab/
Author: Justin Forest
Author-email: hex@umonkey.net
License: GNU GPL
Platform: UNKNOWN
Classifier: Development Status :: 4 - Beta
Classifier: Intended Audience :: Developers
Classifier: License :: OSI Approved :: GNU General Public License (GPL)
Classifier: Programming Language :: Python :: 2
Classifier: Topic :: Software Development :: Bug Tracking
Requires: json
